ai_chen_life_index/RFB_img_cla.py
ai_chen_life_index/RFB_reg.py
ai_chen_life_index/__init__.py
ai_chen_life_index/constant.py
ai_chen_life_index/main.py
ai_chen_life_index/preprocessing.py
ai_chen_life_index/rating.py
ai_chen_life_index/table_reader.py
ai_chen_life_index/test.py
ai_chen_life_index/test_prediction.py
ai_chen_life_index/utils.py
ai_chen_life_index/visual_with_model.py
Cclipy-1.3.2.dist-info/LICENSE
Cclipy-1.3.2.dist-info/METADATA
Cclipy-1.3.2.dist-info/WHEEL
Cclipy-1.3.2.dist-info/top_level.txt
Cclipy-1.3.2.dist-info/RECORD
